alt_src/__init__.py
alt_src/alt_src.py
alt_src-1.6.3.dist-info/LICENSE
alt_src-1.6.3.dist-info/METADATA
alt_src-1.6.3.dist-info/WHEEL
alt_src-1.6.3.dist-info/entry_points.txt
alt_src-1.6.3.dist-info/top_level.txt
alt_src-1.6.3.dist-info/RECORD
