Metadata-Version: 2.1
Name: alt-src
Version: 1.6.3
Summary: Tool for uploading custom patches to centos source rpm repositories
Home-page: https://github.com/release-engineering/alt-src
License: GNU General Public License
Project-URL: Changelog, https://github.com/release-engineering/alt-src/blob/master/CHANGELOG.md
Platform: UNKNOWN
Classifier: Development Status :: 4 - Beta
Classifier: Intended Audience :: Developers
Classifier: Programming Language :: Python :: 2
Classifier: Programming Language :: Python :: 2.4
Classifier: Programming Language :: Python :: 2.6
Classifier: Programming Language :: Python :: 2.7
Classifier: Programming Language :: Python :: 3
Classifier: License :: OSI Approved :: GNU General Public License v3 or later (GPLv3+)
Requires-Dist: koji
Requires-Dist: rpm-py-installer
Requires-Dist: requests
Requires-Dist: PyYAML
Requires-Dist: simplejson
Requires-Dist: six >=1.8.0
